tvsubs_rename-0.1.2.data/scripts/tvsubs_rename
tvsubs_rename-0.1.2.dist-info/metadata.json
tvsubs_rename-0.1.2.dist-info/RECORD
tvsubs_rename-0.1.2.dist-info/METADATA
tvsubs_rename-0.1.2.dist-info/WHEEL
tvsubs_rename-0.1.2.dist-info/top_level.txt
tvsubs_rename-0.1.2.dist-info/DESCRIPTION.rst
tvsubs_rename/__init__.py
tvsubs_rename/tvsubs_rename.py
