Metadata-Version: 2.0
Name: tvsubs-rename
Version: 0.1.2
Summary: Script to mass-rename subtitles
Home-page: https://github.com/eliasdorneles/tvsubs_rename
Author: Elias Dorneles
Author-email: eliasdorneles@gmail.com
License: BSD
Keywords: tvsubs_rename
Platform: UNKNOWN
Classifier: Development Status :: 2 - Pre-Alpha
Classifier: Intended Audience :: Developers
Classifier: License :: OSI Approved :: BSD License
Classifier: Natural Language :: English
Classifier: Programming Language :: Python :: 2
Classifier: Programming Language :: Python :: 2.6
Classifier: Programming Language :: Python :: 2.7
Classifier: Programming Language :: Python :: 3
Classifier: Programming Language :: Python :: 3.3
Classifier: Programming Language :: Python :: 3.4
